.DS_Store
SDP.py
user_data.db
SDPPublishTool-0.0.3.dist-info/METADATA
SDPPublishTool-0.0.3.dist-info/RECORD
SDPPublishTool-0.0.3.dist-info/WHEEL
SDPPublishTool-0.0.3.dist-info/top_level.txt
dataBase/__init__.py
dataBase/__init__.pyc
dataBase/dataBase.py
dataBase/dataBase.pyc
main/__init__.py
main/__init__.pyc
main/main.py
main/main.pyc
