Metadata-Version: 2.1
Name: SDPPublishTool
Version: 0.0.3
Summary: SDP publish
Home-page: UNKNOWN
Author: tanzou
Author-email: tanzou34@gmail.com
License: MIT Licence
Keywords: pip,SDP
Platform: any
Requires-Dist: splinter
Requires-Dist: getpass2
